vital_agent_container/__init__.py
vital_agent_container/agent_container_app.py
vital_agent_container/config/__init__.py
vital_agent_container/handler/__init__.py
vital_agent_container/handler/aimp_message_handler_inf.py
vital_agent_container/handler/impl/__init__.py
vital_agent_container/handler/impl/aimp_echo_message_handler.py
vital_agent_container/processor/__init__.py
vital_agent_container/processor/aimp_message_processor.py
vital_agent_container/streaming/__init__.py
vital_agent_container/streaming/custom_streaming_response.py
vital_agent_container/tasks/__init__.py
vital_agent_container/tasks/request_task.py
vital_agent_container/tasks/task_manager_async_client.py
vital_agent_container/utils/__init__.py
vital_agent_container/utils/aws_utils.py
vital_agent_container/utils/config_utils.py
vital_agent_container/utils/jwt_utils.py
vital_agent_container_sdk-0.1.16.dist-info/licenses/LICENSE
vital_agent_container_sdk-0.1.16.dist-info/METADATA
vital_agent_container_sdk-0.1.16.dist-info/WHEEL
vital_agent_container_sdk-0.1.16.dist-info/top_level.txt
vital_agent_container_sdk-0.1.16.dist-info/RECORD
