Metadata-Version: 2.4
Name: vital-agent-container-sdk
Version: 0.1.16
Summary: Vital Agent Container SDK
Author-email: Marc Hadfield <marc@vital.ai>
License: Apache License 2.0
Project-URL: Homepage, https://github.com/vital-ai/vital-agent-container-python
Project-URL: Repository, https://github.com/vital-ai/vital-agent-container-python
Project-URL: Issues, https://github.com/vital-ai/vital-agent-container-python/issues
Classifier: Programming Language :: Python :: 3.12
Classifier: License :: OSI Approved :: Apache Software License
Classifier: Operating System :: OS Independent
Classifier: Development Status :: 4 - Beta
Classifier: Intended Audience :: Developers
Classifier: Topic :: Software Development :: Libraries :: Python Modules
Requires-Python: >=3.12
License-File: LICENSE
Requires-Dist: vital-ai-vitalsigns>=0.1.32
Requires-Dist: vital-ai-aimp>=0.1.12
Requires-Dist: httpx>=0.28.0
Requires-Dist: python-json-logger>=2.0.7
Requires-Dist: python-dotenv>=1.0.1
Requires-Dist: uvicorn[standard]>=0.35.0
Requires-Dist: fastapi>=0.116.0
Requires-Dist: starlette>=0.36.3
Requires-Dist: pyyaml>=6.0.1
Requires-Dist: requests>=2.31.0
Requires-Dist: pyjwt>=2.8.0
Requires-Dist: cryptography>=41.0.0
Provides-Extra: dev
Requires-Dist: build>=1.0.0; extra == "dev"
Requires-Dist: pytest>=7.0.0; extra == "dev"
Requires-Dist: pytest-asyncio>=0.21.0; extra == "dev"
Requires-Dist: pytest-cov>=4.0.0; extra == "dev"
Requires-Dist: black>=23.0.0; extra == "dev"
Requires-Dist: isort>=5.12.0; extra == "dev"
Requires-Dist: flake8>=6.0.0; extra == "dev"
Requires-Dist: mypy>=1.0.0; extra == "dev"
Requires-Dist: pre-commit>=3.0.0; extra == "dev"
Provides-Extra: docs
Requires-Dist: sphinx>=6.0.0; extra == "docs"
Requires-Dist: sphinx-rtd-theme>=1.2.0; extra == "docs"
Dynamic: license-file
